[
  {
    "VCO-1": { "PITCH": 59, "MOD-DEPTH": 64 },
    "VCO-2": { "PITCH": 49, "MOD-DEPTH": 64 },
    "VCO-3": { "PITCH": 47, "MOD-DEPTH": 64 },
    "VCO-4": { "PITCH": 40, "MOD-DEPTH": 64 }
  },
  {
    "VCO-1": { "PITCH": 62, "MOD-DEPTH": 62 },
    "VCO-2": { "PITCH": 51, "MOD-DEPTH": 65 },
    "VCO-3": { "PITCH": 47, "MOD-DEPTH": 64 },
    "VCO-4": { "PITCH": 39, "MOD-DEPTH": 64 }
  },
  {
    "VCO-1": { "PITCH": 64, "MOD-DEPTH": 62 },
    "VCO-2": { "PITCH": 44, "MOD-DEPTH": 65 },
    "VCO-3": { "PITCH": 47, "MOD-DEPTH": 64 },
    "VCO-4": { "PITCH": 21, "MOD-DEPTH": 66 }
  }
]
